pushwoosh-1.0.2.dist-info/WHEEL
pushwoosh-1.0.2.dist-info/metadata.json
pushwoosh-1.0.2.dist-info/RECORD
pushwoosh-1.0.2.dist-info/METADATA
pushwoosh-1.0.2.dist-info/top_level.txt
pushwoosh-1.0.2.dist-info/DESCRIPTION.rst
pushwoosh/__init__.py
